MANIFEST.in
NEWS.txt
README.rst
setup.py
src/logtogss/__init__.py
src/logtogss/oneshot.py
src/logtogss.egg-info/PKG-INFO
src/logtogss.egg-info/SOURCES.txt
src/logtogss.egg-info/dependency_links.txt
src/logtogss.egg-info/entry_points.txt
src/logtogss.egg-info/not-zip-safe
src/logtogss.egg-info/requires.txt
src/logtogss.egg-info/top_level.txt