Metadata-Version: 1.0
Name: logtogss
Version: 0.1
Summary: Log rows to a Google SpreadSheet
Home-page: https://github.com/haridsv/logss
Author: Hari Dara
Author-email: haridara@gmail.com
License: BSD 2-Clause
Keywords: gdata google spreadsheet csv import
Platform: UNKNOWN
